{"cameraMode":{"drawMode":0,"name":"Shaded","section":"Shading Mode"},"sceneLighting":true,"audioPlay":false,"sceneViewState":{"m_AlwaysRefresh":false,"showFog":true,"showSkybox":true,"showFlares":true,"showImageEffects":true,"showParticleSystems":true,"showVisualEffectGraphs":true,"m_FxEnabled":true},"in2DMode":false,"pivot":{"x":0.6097981333732605,"y":-4.251834869384766,"z":8.505993843078614},"rotation":{"x":0.658928632736206,"y":0.0022566679399460556,"z":-0.0019765847828239204,"w":0.7521980404853821},"size":25.163793563842775,"orthographic":false}